koalas/__init__.py
koalas/coalas.py
coalas-0.0.1.dist-info/LICENSE
coalas-0.0.1.dist-info/METADATA
coalas-0.0.1.dist-info/WHEEL
coalas-0.0.1.dist-info/top_level.txt
coalas-0.0.1.dist-info/RECORD
