Metadata-Version: 2.1
Name: coalas
Version: 0.0.1
Summary: A array based way of dealing with csv files
Home-page: https://github.com/TheArctesian/koalas
Author: arctesian
Author-email: me@danielokita.com
Project-URL: Bug Tracker, https://github.com/TheArctesian/koalas/issues
Classifier: Programming Language :: Python :: 3
Classifier: License :: OSI Approved :: GNU General Public License v3 or later (GPLv3+)
Classifier: Natural Language :: English
Requires-Python: >=3.6
License-File: LICENSE
